Metadata-Version: 1.1
Name: brahma-agi
Version: 0.0.1
Summary: A library for Artificial General Intelligence
Home-page: UNKNOWN
Author: DR.A.SANJAY
Author-email: dr.sanjayanbu@gmail.com
License: MIT
Keywords: AGI
Platform: UNKNOWN
Classifier: Development Status :: 5 - Production/Stable
Classifier: Intended Audience :: Education
Classifier: Operating System :: Microsoft :: Windows :: Windows 10
Classifier: License :: OSI Approved :: MIT License
Classifier: Programming Language :: Python :: 3
